solovision/__init__.py
solovision/appearance/__init__.py
solovision/appearance/backbones/__init__.py
solovision/appearance/backbones/clip/__init__.py
solovision/appearance/backbones/clip/clip/__init__.py
solovision/appearance/backbones/clip/clip/bpe_simple_vocab_16e6.txt.gz
solovision/appearance/backbones/clip/clip/clip.py
solovision/appearance/backbones/clip/clip/model.py
solovision/appearance/backbones/clip/clip/simple_tokenizer.py
solovision/appearance/backbones/clip/config/__init__.py
solovision/appearance/backbones/clip/config/defaults.py
solovision/appearance/backbones/clip/config/defaults_base.py
solovision/appearance/backbones/clip/make_model.py
solovision/appearance/backbones/clip/make_model_clipreid.py
solovision/appearance/backbones/osnet.py
solovision/appearance/backbones/osnet_ain.py
solovision/appearance/backbones/resnet.py
solovision/appearance/backends/base_backend.py
solovision/appearance/backends/onnx_backend.py
solovision/appearance/backends/openvino_backend.py
solovision/appearance/backends/pytorch_backend.py
solovision/appearance/backends/tensorrt_backend.py
solovision/appearance/backends/tflite_backend.py
solovision/appearance/backends/torchscript_backend.py
solovision/appearance/exporters/base_exporter.py
solovision/appearance/exporters/onnx_exporter.py
solovision/appearance/exporters/openvino_exporter.py
solovision/appearance/exporters/tensorrt_exporter.py
solovision/appearance/exporters/tflite_exporter.py
solovision/appearance/exporters/torchscript_exporter.py
solovision/appearance/reid_auto_backend.py
solovision/appearance/reid_export.py
solovision/appearance/reid_model_factory.py
solovision/cli.py
solovision/configs/__init__.py
solovision/configs/bytetrack.yaml
solovision/data/__init__.py
solovision/data/loader.py
solovision/detectors/__init__.py
solovision/detectors/yolo_interface.py
solovision/detectors/yolonas.py
solovision/detectors/yolov8.py
solovision/detectors/yolov9.py
solovision/detectors/yolox.py
solovision/inference.py
solovision-0.0.1.dist-info/entry_points.txt
solovision-0.0.1.dist-info/LICENSE
solovision-0.0.1.dist-info/METADATA
solovision-0.0.1.dist-info/WHEEL
solovision-0.0.1.dist-info/RECORD
