Metadata-Version: 2.1
Name: solovision
Version: 0.0.1
Summary: State-of-the-art Real Time Object Detection & Tracking System integrated with ReID architecture 
License: AGPL-3.0
Keywords: Object tracking,ReID,machine-learning,deep-learning,vision,Artificial Intelligence,YOLO
Author: Dhruv Diddi
Requires-Python: >=3.9, !=2.7.*, !=3.0.*, !=3.1.*, !=3.2.*, !=3.3.*, !=3.4.*, !=3.5.*, !=3.6.*, !=3.7.*, !=3.8.*
Classifier: Development Status :: 4 - Beta
Classifier: Intended Audience :: Developers
Classifier: Intended Audience :: Education
Classifier: Intended Audience :: Science/Research
Classifier: License :: OSI Approved :: GNU Affero General Public License v3
Classifier: License :: OSI Approved :: GNU Affero General Public License v3 or later (AGPLv3+)
Classifier: Programming Language :: Python :: 3
Classifier: Programming Language :: Python :: 3.9
Classifier: Programming Language :: Python :: 3.10
Classifier: Programming Language :: Python :: 3.11
Classifier: Programming Language :: Python :: 3.12
Classifier: Programming Language :: Python :: 3.13
Classifier: Topic :: Scientific/Engineering
Classifier: Topic :: Scientific/Engineering :: Artificial Intelligence
Classifier: Topic :: Scientific/Engineering :: Image Processing
Classifier: Topic :: Scientific/Engineering :: Image Recognition
Classifier: Topic :: Software Development
Requires-Dist: filterpy (>=1.4.5,<2.0.0)
Requires-Dist: ftfy (>=6.1.3,<7.0.0)
Requires-Dist: gdown (>=5.1.0,<6.0.0)
Requires-Dist: gitpython (>=3.1.42,<4.0.0)
Requires-Dist: lapx (>=0.5.5,<0.6.0)
Requires-Dist: loguru (>=0.7.2,<0.8.0)
Requires-Dist: matplotlib (<=3.9.2)
Requires-Dist: numpy (==1.26.4)
Requires-Dist: opencv-python (>=4.7.0,<5.0.0)
Requires-Dist: pandas (>=2.0.0,<3.0.0)
Requires-Dist: pyyaml (>=6.0.1,<7.0.0)
Requires-Dist: regex (>=2024.0.0,<2025.0.0)
Requires-Dist: scikit-learn (>=1.3.0,<2.0.0)
Requires-Dist: streamlit (>=1.29.0,<2.0.0)
Requires-Dist: torch (>=2.2.1,<3.0.0) ; sys_platform == "darwin"
Requires-Dist: torch (>=2.2.1,<3.0.0) ; sys_platform == "linux" or sys_platform == "win32"
Requires-Dist: torchvision (>=0.17.1,<0.18.0) ; sys_platform == "darwin"
Requires-Dist: torchvision (>=0.17.1,<0.18.0) ; sys_platform == "linux" or sys_platform == "win32"
Requires-Dist: yacs (>=0.1.8,<0.2.0)
